starbot/__init__.py
starbot/core/__init__.py
starbot/core/bot.py
starbot/core/datasource.py
starbot/core/dynamic.py
starbot/core/live.py
starbot/core/model.py
starbot/core/room.py
starbot/core/sender.py
starbot/core/server.py
starbot/core/user.py
starbot/exception/ApiException.py
starbot/exception/AtAllLimitedException.py
starbot/exception/CredentialNoBiliJctException.py
starbot/exception/CredentialNoBuvid3Exception.py
starbot/exception/CredentialNoSessdataException.py
starbot/exception/DataSourceException.py
starbot/exception/LiveException.py
starbot/exception/NetworkException.py
starbot/exception/NoPermissionException.py
starbot/exception/RedisException.py
starbot/exception/ResponseCodeException.py
starbot/exception/ResponseException.py
starbot/exception/__init__.py
starbot/painter/DynamicPicGenerator.py
starbot/painter/LiveReportGenerator.py
starbot/painter/PicGenerator.py
starbot/painter/RankingGenerator.py
starbot/painter/__init__.py
starbot/utils/AsyncEvent.py
starbot/utils/Credential.py
starbot/utils/Danmaku.py
starbot/utils/__init__.py
starbot/utils/config.py
starbot/utils/network.py
starbot/utils/redis.py
starbot/utils/utils.py
bili_to_tele-1.0.1.dist-info/LICENSE
bili_to_tele-1.0.1.dist-info/METADATA
bili_to_tele-1.0.1.dist-info/WHEEL
bili_to_tele-1.0.1.dist-info/entry_points.txt
bili_to_tele-1.0.1.dist-info/top_level.txt
bili_to_tele-1.0.1.dist-info/RECORD
