Metadata-Version: 2.1
Name: bili-to-tele
Version: 1.0.1
Summary: A tool to push Bilibili live and dynamic updates to Telegram
Home-page: https://github.com/YourUsername/bili_to_tele
Author: aiko
Author-email: hideonbushplease774@gmail.com
License: MIT
Keywords: bilibili telegram push notifications
Classifier: Programming Language :: Python :: 3
Classifier: License :: OSI Approved :: MIT License
Classifier: Operating System :: OS Independent
Requires-Python: >=3.7
License-File: LICENSE
Requires-Dist: httpx>=0.23.0
Requires-Dist: loguru>=0.5.3
Requires-Dist: pydantic>=1.10.2
Requires-Dist: aiomysql>=0.1.1
Requires-Dist: pymysql>=1.0.2
Requires-Dist: aiohttp>=3.8.1
Requires-Dist: brotli>=1.0.9
Requires-Dist: creart>=0.1.4
